glitter_sdk/__init__.py
glitter_sdk/connection.py
glitter_sdk/driver.py
glitter_sdk/exceptions.py
glitter_sdk/pool.py
glitter_sdk/transport.py
glitter_sdk/utils.py
tests/__init__.py
tests/test_onebyone.py
glitter_sdk_test-0.1.0.dist-info/LICENSE
glitter_sdk_test-0.1.0.dist-info/METADATA
glitter_sdk_test-0.1.0.dist-info/WHEEL
glitter_sdk_test-0.1.0.dist-info/top_level.txt
glitter_sdk_test-0.1.0.dist-info/RECORD
