Metadata-Version: 2.1
Name: glitter-sdk-test
Version: 0.1.0
Summary: Glitter Protocol is a blockchain based database and index engine for developing and hosting web3 applications in decentralized storage networks.
Home-page: https://docs.glitterprotocol.io/
Author: ted
Author-email: ted@glitterprotocol.io
License: UNKNOWN
Platform: UNKNOWN
Requires-Python: >=3.5
License-File: LICENSE
Requires-Dist: requests
Provides-Extra: dev
Requires-Dist: ipdb ; extra == 'dev'
Requires-Dist: ipython ; extra == 'dev'
Requires-Dist: pre-commit ; extra == 'dev'
Requires-Dist: pytest (>=7.0.1) ; extra == 'dev'
Requires-Dist: Sphinx (~=4.0) ; extra == 'dev'
Requires-Dist: sphinx-autobuild ; extra == 'dev'
Requires-Dist: sphinxcontrib-autorun ; extra == 'dev'
Requires-Dist: sphinxcontrib-napoleon (>=0.4.4) ; extra == 'dev'
Requires-Dist: sphinx-rtd-theme ; extra == 'dev'
Requires-Dist: sphinxcontrib-httpdomain ; extra == 'dev'
Provides-Extra: docs
Requires-Dist: Sphinx (~=4.0) ; extra == 'docs'
Requires-Dist: sphinx-autobuild ; extra == 'docs'
Requires-Dist: sphinxcontrib-autorun ; extra == 'docs'
Requires-Dist: sphinxcontrib-napoleon (>=0.4.4) ; extra == 'docs'
Requires-Dist: sphinx-rtd-theme ; extra == 'docs'
Requires-Dist: sphinxcontrib-httpdomain ; extra == 'docs'
Provides-Extra: test
Requires-Dist: pytest (>=7.0.1) ; extra == 'test'
